MANIFEST.in
README.md
setup.py
django_export_action_py3.egg-info/PKG-INFO
django_export_action_py3.egg-info/SOURCES.txt
django_export_action_py3.egg-info/dependency_links.txt
django_export_action_py3.egg-info/not-zip-safe
django_export_action_py3.egg-info/requires.txt
django_export_action_py3.egg-info/top_level.txt
export_action/__init__.py
export_action/admin.py
export_action/introspection.py
export_action/report.py
export_action/urls.py
export_action/views.py
export_action/templates/export_action/export.html
export_action/templates/export_action/fields.html
export_action/templates/export_action/report_html.html