Metadata-Version: 2.1
Name: django-export-action-py3
Version: 0.6
Summary: Generic export action for Django's Admin for Python 3.6 and Django 2.x
Home-page: https://github.com/juanjosegb/django-export-action_py3
Author: Juan José Garcia
Author-email: juanjose.garciabeza@hotmail.com
License: MIT
Keywords: django-export-action-py3
Platform: UNKNOWN
Classifier: Development Status :: 3 - Alpha
Classifier: Framework :: Django
Classifier: Framework :: Django :: 1.8
Classifier: Framework :: Django :: 1.9
Classifier: Framework :: Django :: 1.10
Classifier: Framework :: Django :: 1.11
Classifier: Framework :: Django :: 2.2
Classifier: Intended Audience :: Developers
Classifier: License :: OSI Approved :: BSD License
Classifier: Natural Language :: English
Classifier: Programming Language :: Python :: 2
Classifier: Programming Language :: Python :: 2.7
Classifier: Programming Language :: Python :: 3
Classifier: Programming Language :: Python :: 3.4
Classifier: Programming Language :: Python :: 3.5
Classifier: Programming Language :: Python :: 3.6
